dahood/__init__.py
dahood/dahood.py
dahood-0.0.3.dist-info/METADATA
dahood-0.0.3.dist-info/WHEEL
dahood-0.0.3.dist-info/license.txt
dahood-0.0.3.dist-info/top_level.txt
dahood-0.0.3.dist-info/RECORD
