Metadata-Version: 2.1
Name: dahood
Version: 0.0.3
Summary: Dahood is used for LuaU implementation into Python projects, used by celex and howl
Classifier: Programming Language :: Python :: 3
Classifier: License :: OSI Approved :: MIT License
Classifier: Operating System :: OS Independent
Requires-Python: >=3.6
License-File: license.txt
